CirclesVacanciesScrapers/__init__.py
CirclesVacanciesScrapers/database_vacancies.py
CirclesVacanciesScrapers/indeed_com_scraper.py
CirclesVacanciesScrapers/monster_com_scraper.py
local_recruitment_employer_python_backend-0.0.17.dist-info/METADATA
local_recruitment_employer_python_backend-0.0.17.dist-info/WHEEL
local_recruitment_employer_python_backend-0.0.17.dist-info/top_level.txt
local_recruitment_employer_python_backend-0.0.17.dist-info/RECORD
